autoboot/__init__.py
autoboot/application_properties.py
autoboot/applications.py
autoboot/args.py
autoboot/autoboot.schema.json
autoboot/logging.py
autoboot/server_properties.py
autoboot/annotation/__init__.py
autoboot/annotation/component.py
autoboot/annotation/effect.py
autoboot/annotation/env.py
autoboot/annotation/log.py
autoboot/event/__init__.py
autoboot/event/application_listener.py
autoboot/event/component_listener.py
autoboot/event/event_emitter.py
autoboot/meta/__init__.py
autoboot/meta/listener.py
autoboot/meta/property.py
autoboot/plugin/__init__.py
autoboot/plugin/app_plugin.py
autoboot/plugin/app_plugin_metaclass.py
autoboot/process/__init__.py
autoboot/process/env_process.py
autoboot/process/yaml_constructors.py
autoboot/process/yaml_parser.py
autoboot/thread/__init__.py
autoboot/thread/thread_pool.py
autoboot/util/__init__.py
autoboot/util/capacity.py
autoboot/util/json_model.py
autoboot/util/local_cache.py
autoboot/util/object_navigator.py
autoboot/util/time_duration.py
autoboot/util/type_reflect.py
autoboot-0.12.2.dist-info/LICENSE.txt
autoboot-0.12.2.dist-info/METADATA
autoboot-0.12.2.dist-info/WHEEL
autoboot-0.12.2.dist-info/top_level.txt
autoboot-0.12.2.dist-info/RECORD
