Metadata-Version: 2.1
Name: autoboot
Version: 0.12.2
Summary: IoC with auto config framework
Home-page: https://github.com/yizzuide/autoboot
Author: yizzuide
Author-email: fu837014586@163.com
License: MIT
Keywords: IoC,event,auto config
Classifier: Development Status :: 5 - Production/Stable
Classifier: Operating System :: OS Independent
Classifier: Intended Audience :: Developers
Classifier: Programming Language :: Python :: 3.8
Classifier: License :: OSI Approved :: MIT License
Requires-Python: >=3.8
License-File: LICENSE.txt
Requires-Dist: python-dotenv <2.0,>=1.0.0
Requires-Dist: filetype <2.0,>=1.2.0
Requires-Dist: loguru <1.0,>=0.7.0
Requires-Dist: pyyaml <7.0,>=6.0.1
Requires-Dist: wrapt <2.0,>=1.14.1
Requires-Dist: pydantic <3.0.0,>=2.6.4
Requires-Dist: result <1.0,>=0.14.0
Requires-Dist: whenever <1.0,>=0.6.0
Requires-Dist: tzlocal <6.0,>=5.1.0
Requires-Dist: jmespath <2.0,>=1.0.1
Requires-Dist: more-itertools <11.0,>=10.1.0
Requires-Dist: cytoolz <1.0,>=0.12.3
